pysubsonic/__init__.py
pysubsonic/api.py
pysubsonic-0.1.0.dist-info/METADATA
pysubsonic-0.1.0.dist-info/WHEEL
pysubsonic-0.1.0.dist-info/licenses/LICENSE
pysubsonic-0.1.0.dist-info/RECORD
