Metadata-Version: 2.1
Name: pysubsonic
Version: 0.1.0
Summary: Mostly (in)complete subsonic api
Project-URL: Homepage, https://gitea.xhec.dev/matt/pysubsonic
Project-URL: Bug Tracker, https://gitea.xhec.dev/matt/pysubsonic/issues
Project-URL: Documentation, https://xhec.dev/pysubsonic/
Author-email: Matt C <matt@xhec.dev>
License: MIT License
License-File: LICENSE
Classifier: License :: OSI Approved :: MIT License
Classifier: Operating System :: OS Independent
Classifier: Programming Language :: Python :: 3
Requires-Python: >=3.7
Requires-Dist: beautifulsoup4
Requires-Dist: lxml
Requires-Dist: requests
